expense_bot/__init__.py
expense_bot/bot.py
expense_bot-0.1.0.dist-info/METADATA
expense_bot-0.1.0.dist-info/WHEEL
expense_bot-0.1.0.dist-info/entry_points.txt
expense_bot-0.1.0.dist-info/top_level.txt
expense_bot-0.1.0.dist-info/RECORD
