Metadata-Version: 2.4
Name: expense_bot
Version: 0.1.0
Summary: A Telegram bot for monthly expense calculation
Home-page: https://github.com/asm-shaikat
Author: Your Name
Classifier: Programming Language :: Python :: 3
Classifier: License :: OSI Approved :: MIT License
Requires-Python: >=3.7
Requires-Dist: python-telegram-bot==20.3
Dynamic: author
Dynamic: classifier
Dynamic: description-content-type
Dynamic: home-page
Dynamic: requires-dist
Dynamic: requires-python
Dynamic: summary
